inputty/__init__.py
inputty/_version.py
inputty/xxx.py
inputty/src/__init__.py
inputty/src/colours.py
inputty/src/input.py
inputty/tests/__init__.py
inputty/tests/test_input.py
inputty/tests/test_prompt.py
inputty-1.0.5.dist-info/LICENSE.txt
inputty-1.0.5.dist-info/METADATA
inputty-1.0.5.dist-info/WHEEL
inputty-1.0.5.dist-info/top_level.txt
inputty-1.0.5.dist-info/RECORD
