Metadata-Version: 2.1
Name: inputty
Version: 1.0.5
Summary: """A collection of modules that supports cCLI inputs."""
Home-page: https://psionman@bitbucket.org/psionman/bfgdealer.git
Download-URL: https://pypi.org/project/bfgdealer/
Author: jeff watkins
Author-email: support@bidforgame.com
License: MIT
Keywords: cli,input
License-File: LICENSE.txt
